cbr_custom_data_feeds/__init__.py
cbr_custom_data_feeds/config/__init__.py
cbr_custom_data_feeds/data_feeds/Data_Feeds__Files.py
cbr_custom_data_feeds/data_feeds/Data_Feeds__Http_Content.py
cbr_custom_data_feeds/data_feeds/Data_Feeds__S3_DB.py
cbr_custom_data_feeds/data_feeds/Data_Feeds__S3__Key_Generator.py
cbr_custom_data_feeds/data_feeds/Data__Feeds__Shared_Constants.py
cbr_custom_data_feeds/data_feeds/__init__.py
cbr_custom_data_feeds/data_feeds/models/Model__Data_Feeds__Prompt.py
cbr_custom_data_feeds/data_feeds/models/Model__Data_Feeds__Providers.py
cbr_custom_data_feeds/data_feeds/models/Model__Data_Feeds__Raw_Data.py
cbr_custom_data_feeds/data_feeds/models/__init__.py
cbr_custom_data_feeds/fast_api/Data_Feeds__Fast_API.py
cbr_custom_data_feeds/fast_api/__init__.py
cbr_custom_data_feeds/fast_api/routes/Routes__Info.py
cbr_custom_data_feeds/fast_api/routes/__init__.py
cbr_custom_data_feeds/lambdas/__init__.py
cbr_custom_data_feeds/lambdas/handler.py
cbr_custom_data_feeds/providers/__init__.py
cbr_custom_data_feeds/providers/cyber_security/__init__.py
cbr_custom_data_feeds/providers/cyber_security/__to_create_integration/notes.txt
cbr_custom_data_feeds/providers/cyber_security/__to_create_integration/reddit/notes.txt
cbr_custom_data_feeds/providers/cyber_security/__to_create_integration/the_stack/notes.txt
cbr_custom_data_feeds/providers/cyber_security/hacker_news/Hacker_News__Files.py
cbr_custom_data_feeds/providers/cyber_security/hacker_news/Hacker_News__Http_Content.py
cbr_custom_data_feeds/providers/cyber_security/hacker_news/Hacker_News__Parser.py
cbr_custom_data_feeds/providers/cyber_security/hacker_news/Hacker_News__Prompt_Creator.py
cbr_custom_data_feeds/providers/cyber_security/hacker_news/Hacker_News__S3_DB.py
cbr_custom_data_feeds/providers/cyber_security/hacker_news/__init__.py
cbr_custom_data_feeds/providers/cyber_security/hacker_news/models/Model__Hacker_News__Article.py
cbr_custom_data_feeds-1.21.0.dist-info/LICENSE
cbr_custom_data_feeds-1.21.0.dist-info/METADATA
cbr_custom_data_feeds-1.21.0.dist-info/WHEEL
cbr_custom_data_feeds-1.21.0.dist-info/RECORD
