Metadata-Version: 2.1
Name: cbr_custom_data_feeds
Version: 1.21.0
Summary: CBR Custom - Data Feeds
Home-page: https://github.com/the-cyber-boardroom/cbr-custom--data-feeds
License: Apache 2.0
Author: Dinis Cruz
Author-email: dinis.cruz@owasp.org
Requires-Python: >=3.11,<4.0
Classifier: License :: Other/Proprietary License
Classifier: Programming Language :: Python :: 3
Classifier: Programming Language :: Python :: 3.11
Classifier: Programming Language :: Python :: 3.12
Classifier: Programming Language :: Python :: 3.13
Requires-Dist: bs4
Requires-Dist: httpx
Requires-Dist: mangum
Requires-Dist: osbot-aws
Requires-Dist: osbot-fast-api
Requires-Dist: osbot-local-stack
Requires-Dist: osbot-utils
Requires-Dist: uvicorn
Project-URL: Repository, https://github.com/the-cyber-boardroom/cbr-custom--data-feeds
